README.md
setup.cfg
setup.py
aiPool/__init__.py
aiPool.egg-info/PKG-INFO
aiPool.egg-info/SOURCES.txt
aiPool.egg-info/dependency_links.txt
aiPool.egg-info/requires.txt
aiPool.egg-info/top_level.txt
aiPool.egg-info/zip-safe
aiPool/text_classification/CorpusBunch.py
aiPool/text_classification/CorpusSegment.py
aiPool/text_classification/NBayesPredict.py
aiPool/text_classification/OSSUpload.py
aiPool/text_classification/OssUtils.py
aiPool/text_classification/TFIDFSpace.py
aiPool/text_classification/TextClassification.py
aiPool/text_classification/Tools.py
aiPool/text_classification/ZipUtils.py
aiPool/text_classification/__init__.py