Metadata-Version: 1.2
Name: aiPool
Version: 1.1
Summary: Framework for Advanced Statistics and Data Sciences
Home-page: https://github.com/luoaijun/com.luoaijun.data.git
Author: luoaijun
Author-email: 3191287315@qq.com
Maintainer: luoaijun
Maintainer-email: 3191287315@qq.com
License: UNKNOWN
Project-URL: github.io, https://luoaijun.github.io/self
Keywords: knn ml svm tree NaiveBayes AdbBoost
Platform: UNKNOWN
Classifier: Development Status :: 5 - Production/Stable
Classifier: Intended Audience :: Developers
Classifier: Topic :: Software Development :: Code Generators
Classifier: License :: OSI Approved :: MIT License
Classifier: Programming Language :: Python :: 3
Classifier: Programming Language :: Python :: 3.4
Classifier: Programming Language :: Python :: 3.5
Classifier: Programming Language :: Python :: 3.6
Classifier: Programming Language :: Python :: 3.7
